.DS_Store
gbx_lm/.DS_Store
gbx_lm/__init__.py
gbx_lm/chat.py
gbx_lm/evaluate.py
gbx_lm/fastapi_server.py
gbx_lm/gba2mlx.py
gbx_lm/generate.py
gbx_lm/lora.py
gbx_lm/manage.py
gbx_lm/sample_utils.py
gbx_lm/server_utils.py
gbx_lm/tokenizer_utils.py
gbx_lm/utils.py
gbx_lm/version.py
gbx_lm/langchain/README.md
gbx_lm/langchain/__init__.py
gbx_lm/langchain/chat_gbx.py
gbx_lm/langchain/gbx_pipeline.py
gbx_lm/langchain/graph_transformer.py
gbx_lm/models/__init__.py
gbx_lm/models/base.py
gbx_lm/models/cache.py
gbx_lm/models/qdeepseek_v3.py
gbx_lm/models/qllama.py
gbx_lm/models/qmixtral.py
gbx_lm/models/qphi3.py
gbx_lm/models/qqwen2.py
gbx_lm/models/qqwen3.py
gbx_lm/models/qqwen3_moe.py
gbx_lm/models/quantized_linear_gba.py
gbx_lm/models/rope_utils.py
gbx_lm/models/su_rope.py
gbx_lm/models/switch_layers.py
gbx_lm/routing/.DS_Store
gbx_lm/routing/__init__.py
gbx_lm/routing/confidence_scorer.py
gbx_lm/routing/libra_router/.DS_Store
gbx_lm/routing/libra_router/README.md
gbx_lm/routing/libra_router/__init__.py
gbx_lm/routing/libra_router/requirements.txt
gbx_lm/routing/libra_router/ue_router/__init__.py
gbx_lm/routing/libra_router/ue_router/database.py
gbx_lm/routing/libra_router/ue_router/estimator.py
gbx_lm/serve/README.md
gbx_lm/serve/__init__.py
gbx_lm/serve/mlx_fastchat_worker.py
gbx_lm/tuner/__init__.py
gbx_lm/tuner/datasets.py
gbx_lm/tuner/dora.py
gbx_lm/tuner/lora.py
gbx_lm/tuner/trainer.py
gbx_lm/tuner/utils.py
gbx_lm-0.4.1.dist-info/LICENSE
gbx_lm-0.4.1.dist-info/METADATA
gbx_lm-0.4.1.dist-info/WHEEL
gbx_lm-0.4.1.dist-info/entry_points.txt
gbx_lm-0.4.1.dist-info/top_level.txt
gbx_lm-0.4.1.dist-info/RECORD
