Metadata-Version: 2.2
Name: gbx-lm
Version: 0.4.1
Summary: GBA Model Toolkit for MLX
Home-page: https://github.com/GreenBitAI/gbx-lm
Author: GreenBitAI and MLX Contributors
Author-email: team@greenbit.ai
License: Apache-2.0
Keywords: mlx,apple,large language models,llm,language models
Classifier: Development Status :: 4 - Beta
Classifier: Intended Audience :: Developers
Classifier: Intended Audience :: Science/Research
Classifier: Programming Language :: Python :: 3
Classifier: Programming Language :: Python :: 3.9
Classifier: Programming Language :: Python :: 3.10
Classifier: Programming Language :: Python :: 3.11
Classifier: Programming Language :: Python :: 3.12
Classifier: Topic :: Scientific/Engineering :: Artificial Intelligence
Requires-Python: >=3.9
License-File: LICENSE
Requires-Dist: mlx>=0.25.0
Requires-Dist: numpy
Requires-Dist: transformers[sentencepiece]>=4.39.3
Requires-Dist: huggingface_hub
Requires-Dist: torch>=2.0.0
Requires-Dist: protobuf
Requires-Dist: pyyaml
Requires-Dist: datasets
Requires-Dist: fastapi
Requires-Dist: uvicorn
Requires-Dist: pydantic
Provides-Extra: server
Requires-Dist: fastapi; extra == "server"
Requires-Dist: uvicorn; extra == "server"
Requires-Dist: pydantic; extra == "server"
Provides-Extra: langchain
Requires-Dist: langchain-core; extra == "langchain"
Provides-Extra: mlx-lm
Requires-Dist: mlx-lm>=0.24.0; extra == "mlx-lm"
Provides-Extra: dev
Requires-Dist: pytest>=7.0.0; extra == "dev"
Requires-Dist: pytest-asyncio>=0.20.0; extra == "dev"
Requires-Dist: httpx>=0.24.0; extra == "dev"
Provides-Extra: evaluate
Requires-Dist: lm-eval; extra == "evaluate"
Requires-Dist: tqdm; extra == "evaluate"
Provides-Extra: all
Requires-Dist: fastapi; extra == "all"
Requires-Dist: uvicorn; extra == "all"
Requires-Dist: pydantic; extra == "all"
Requires-Dist: langchain-core; extra == "all"
Requires-Dist: mlx-lm>=0.24.0; extra == "all"
Requires-Dist: pytest>=7.0.0; extra == "all"
Requires-Dist: pytest-asyncio>=0.20.0; extra == "all"
Requires-Dist: httpx>=0.24.0; extra == "all"
Requires-Dist: lm-eval; extra == "all"
Requires-Dist: tqdm; extra == "all"
Dynamic: author
Dynamic: author-email
Dynamic: classifier
Dynamic: description
Dynamic: description-content-type
Dynamic: home-page
Dynamic: keywords
Dynamic: license
Dynamic: provides-extra
Dynamic: requires-dist
Dynamic: requires-python
Dynamic: summary
